{"username":"GokloGuklo","access_token":"","init_data":"query_id=AAE6pXYQAwAAADqldhCKVkPR&user=%7B%22id%22%3A6718661946%2C%22first_name%22%3A%22Goklo%20%E2%96%AA%EF%B8%8F%22%2C%22last_name%22%3A%22Guklo.%22%2C%22username%22%3A%22GokloGuklo%22%2C%22language_code%22%3A%22id%22%2C%22allows_write_to_pm%22%3Atrue%2C%22photo_url%22%3A%22https%3A%5C%2F%5C%2Ft.me%5C%2Fi%5C%2Fuserpic%5C%2F320%5C%2FRl9Iq0zE8McShgtKNYWdJyB5nIK6dVOFuWjVIuO-OqQhf2qT6cvhvBqD2Sa5wb71.svg%22%7D&auth_date=1731841800&hash=8918917e054b692c3c70dea104a4b5080cbab56be48021b4e8743fb55152d1fb","use_proxy":true,"proxy_hostname":"162.218.208.245","proxy_protocol":"socks5","proxy_port":6364,"proxy_username":"odnmirws","proxy_password":"b9y2qam5piqn"}