{"username":"HomanTom","access_token":"","init_data":"query_id=AAHQBL0iAwAAANAEvSKzle1o&user=%7B%22id%22%3A7025263824%2C%22first_name%22%3A%22Homan%20%E2%96%AA%EF%B8%8F%22%2C%22last_name%22%3A%22Tom.%22%2C%22username%22%3A%22HomanTom%22%2C%22language_code%22%3A%22id%22%2C%22allows_write_to_pm%22%3Atrue%2C%22photo_url%22%3A%22https%3A%5C%2F%5C%2Ft.me%5C%2Fi%5C%2Fuserpic%5C%2F320%5C%2FU0EHtzOzFaV7dS2FTxsZvjV8rd6P9CwQfM8OIH3S6ZqeqwINrRX0sJTtnOm0zF1B.svg%22%7D&auth_date=1731841482&hash=e4d9ee2116a625647ebb69d739a37f6b6fe170ce1d325600f0127b4fe13f854a","use_proxy":true,"proxy_hostname":"45.41.176.185","proxy_protocol":"socks5","proxy_port":6483,"proxy_username":"odnmirws","proxy_password":"b9y2qam5piqn"}