{"username":"UhoDere","access_token":"","init_data":"query_id=AAGpGxN8AgAAAKkbE3xKfYLV&user=%7B%22id%22%3A6376594345%2C%22first_name%22%3A%22Uho%20%E2%96%AA%EF%B8%8F%22%2C%22last_name%22%3A%22Dere.%22%2C%22username%22%3A%22UhoDere%22%2C%22language_code%22%3A%22id%22%2C%22allows_write_to_pm%22%3Atrue%2C%22photo_url%22%3A%22https%3A%5C%2F%5C%2Ft.me%5C%2Fi%5C%2Fuserpic%5C%2F320%5C%2FgLvynHPoB6kCg40RtLTdPzUSnVMUrs-7tMOpCKeZJVG5OVeXaYHZ2tLxi1UDYPJF.svg%22%7D&auth_date=1731842247&hash=85e13ef7b625249593eab802f6242cdcdbf7d1544a0b2cf8465611bdfc15c86d","use_proxy":true,"proxy_hostname":"45.61.123.242","proxy_protocol":"socks5","proxy_port":5921,"proxy_username":"odnmirws","proxy_password":"b9y2qam5piqn"}