{"username":"CokiuGertu","access_token":"","init_data":"query_id=AAGDp2IGAwAAAIOnYga_bkRo&user=%7B%22id%22%3A6549579651%2C%22first_name%22%3A%22Cokiu%20%F0%9F%8D%85%22%2C%22last_name%22%3A%22Gertu%22%2C%22username%22%3A%22CokiuGertu%22%2C%22language_code%22%3A%22id%22%2C%22allows_write_to_pm%22%3Atrue%7D&auth_date=1725605223&hash=884662633bca0be6afc6888ab5e2f68eb525cf7dabb8ac41a17eb90539784fcd","use_proxy":true,"proxy_hostname":"64.137.89.241","proxy_protocol":"socks5","proxy_port":6314,"proxy_username":"odnmirws","proxy_password":"b9y2qam5piqn"}